{"cameraMode":{"drawMode":0,"name":"Shaded","section":"Shading Mode"},"sceneLighting":true,"audioPlay":false,"sceneViewState":{"showFog":true,"showMaterialUpdate":false,"showSkybox":true,"showFlares":true,"showImageEffects":true,"showParticleSystems":true},"in2DMode":false,"pivot":{"x":4.773809432983398,"y":2.401738405227661,"z":-13.126886367797852},"rotation":{"x":0.002824825467541814,"y":0.9630773067474365,"z":-0.010112697258591652,"w":0.26902711391448977},"size":9.89271354675293,"orthographic":false}